standard_mux.v
module standard_mux
	(
	in_1,
	in_2,
	in_3,
	out_1
	);
	
	input	[3:0]	in_1;
	input	[3:0]	in_2;
	input			in_3;
	
	output	[3:0]	out_1;
	
	assign out_1 = in_3 ? in_2 : in_1;
	
	endmodule

standard_mux_tb.v
module standard_mux_tb ();
	
	reg	[3:0]	in_1;
	reg	[3:0]	in_2;
	reg	in_3;
	
	wire	[3:0]	out_1;

	standard_mux UUT(in_1, in_2, in_3, out_1);
	
	initial begin
	
		$dumpfile("test.vcd");
		$dumpvars(0,standard_mux_tb);
	
		#1	in_1 = 4'b0000;
			in_2 = 4'b0000;
			in_3 = 0;
		
		#1	in_1 = 4'b0001;
			in_2 = 4'b0000;
			in_3 = 0;
	
		#1	in_1 = 4'b0010;
			in_2 = 4'b0000;
			in_3 = 0;
		
		#1	in_1 = 4'b0011;
			in_2 = 4'b0000;
			in_3 = 0;

			
		#1	in_1 = 4'b0000;
			in_2 = 4'b0001;
			in_3 = 1;
		
		#1	in_1 = 4'b0001;
			in_2 = 4'b0001;
			in_3 = 1;
	
		#1	in_1 = 4'b0010;
			in_2 = 4'b0001;
			in_3 = 1;
		
		#1	in_1 = 4'b0011;
			in_2 = 4'b0001;
			in_3 = 1;
	
	
		#1	in_1 = 4'b0000;
			in_2 = 4'b0010;
			in_3 = 1;
		
		#1	in_1 = 4'b0001;
			in_2 = 4'b0010;
			in_3 = 1;
	
		#1	in_1 = 4'b0010;
			in_2 = 4'b0010;
			in_3 = 1;
		
		#1	in_1 = 4'b0011;
			in_2 = 4'b0010;
			in_3 = 1;

			
		#1	in_1 = 4'b0000;
			in_2 = 4'b0011;
			in_3 = 1;
		
		#1	in_1 = 4'b0001;
			in_2 = 4'b0011;
			in_3 = 1;
	
		#1	in_1 = 4'b0010;
			in_2 = 4'b0011;
			in_3 = 1;
		
		#1	in_1 = 4'b0011;
			in_2 = 4'b0011;
			in_3 = 1;
	
	
	
		#1	$finish;
		
		end
		
	endmodule

test.vcd
$date
	Sun Apr 29 07:38:41 2018
$end
$version
	Icarus Verilog
$end
$timescale
	1s
$end
$scope module standard_mux_tb $end
$var wire 4 ! out_1 [3:0] $end
$var reg 4 " in_1 [3:0] $end
$var reg 4 # in_2 [3:0] $end
$var reg 1 $ in_3 $end
$scope module UUT $end
$var wire 4 % in_1 [3:0] $end
$var wire 4 & in_2 [3:0] $end
$var wire 1 $ in_3 $end
$var wire 4 ' out_1 [3:0] $end
$upscope $end
$upscope $end
$enddefinitions $end
#0
$dumpvars
bx '
bx &
bx %
x$
bx #
bx "
bx !
$end
#1
b0 !
b0 '
0$
b0 #
b0 &
b0 "
b0 %
#2
b1 !
b1 '
b1 "
b1 %
#3
b10 !
b10 '
b10 "
b10 %
#4
b11 !
b11 '
b11 "
b11 %
#5
b1 !
b1 '
1$
b1 #
b1 &
b0 "
b0 %
#6
b1 "
b1 %
#7
b10 "
b10 %
#8
b11 "
b11 %
#9
b10 !
b10 '
b10 #
b10 &
b0 "
b0 %
#10
b1 "
b1 %
#11
b10 "
b10 %
#12
b11 "
b11 %
#13
b11 !
b11 '
b11 #
b11 &
b0 "
b0 %
#14
b1 "
b1 %
#15
b10 "
b10 %
#16
b11 "
b11 %
