simple_in_n_out.v
//	SIMPLE IN AND OUT EXAMPLE FROM READLER, B.C.
//

module simple_in_n_out (
	in_1,
	in_2,
	in_3,
	out_1,
	out_2
	);

	input in_1;
	input in_2;
	input in_3;
	output out_1;
	output out_2;
	
	assign out_1 = in_1 & in_2 & in_3;
	assign out_2 = in_1 | in_2 | in_3;
	
	endmodule

simple_in_n_out_tb.v
module simple_in_n_out_tb ();
	
	reg in_1;
	reg in_2;
	reg in_3;
	
	wire out_1;
	wire out_2;

	simple_in_n_out UUT(in_1, in_2, in_3, out_1, out_2);
	
	initial begin
	
		$dumpfile("test.vcd");
		$dumpvars(0,simple_in_n_out_tb);
	
		#1	in_1 = 0;
			in_2 = 0;
			in_3 = 0;
		
		#1	in_1 = 1;
			in_2 = 0;
			in_3 = 0;
	
		#1	in_1 = 0;
			in_2 = 1;
			in_3 = 0;
	
		#1	in_1 = 1;
			in_2 = 1;
			in_3 = 0;
		
		#1	in_1 = 0;
			in_2 = 0;
			in_3 = 1;
		
		#1	in_1 = 1;
			in_2 = 0;
			in_3 = 1;
	
		#1	in_1 = 0;
			in_2 = 1;
			in_3 = 1;
	
		#1	in_1 = 1;
			in_2 = 1;
			in_3 = 1;

		#1	$finish;
		
		end
		
	endmodule

test.vcd
$date
	Sat Apr 28 21:28:11 2018
$end
$version
	Icarus Verilog
$end
$timescale
	1s
$end
$scope module simple_in_n_out_tb $end
$var wire 1 ! out_2 $end
$var wire 1 " out_1 $end
$var reg 1 # in_1 $end
$var reg 1 $ in_2 $end
$var reg 1 % in_3 $end
$scope module UUT $end
$var wire 1 # in_1 $end
$var wire 1 $ in_2 $end
$var wire 1 % in_3 $end
$var wire 1 " out_1 $end
$var wire 1 ! out_2 $end
$upscope $end
$upscope $end
$enddefinitions $end
#0
$dumpvars
x%
x$
x#
x"
x!
$end
#1
0"
0!
0%
0$
0#
#2
1!
1#
#3
1$
0#
#4
1#
#5
1%
0$
0#
#6
1#
#7
1$
0#
#8
1"
1#
